{
  "timestamp": "2026-02-21T17:06:37.144Z",
  "target": "fremont-ca",
  "config": {
    "targetQuestions": 130,
    "batchSize": 25,
    "maxRetries": 3
  },
  "results": {
    "totalGenerated": 0,
    "passedValidation": 0,
    "failedValidation": 0,
    "retryExhausted": 0,
    "finalInserted": 0
  },
  "breakdown": {
    "byRule": {},
    "byRetryAttempt": {},
    "byDifficulty": {
      "easy": 0,
      "medium": 0,
      "hard": 0
    },
    "byTopic": {}
  },
  "failures": [],
  "performance": {
    "totalDurationMs": 78119,
    "apiCalls": 0,
    "tokensUsed": {
      "input": 0,
      "output": 0,
      "cached": 0
    },
    "estimatedCostUsd": 0
  }
}